quoridor/__init__.py
quoridor/src/__init__.py
quoridor/src/exceptions.py
quoridor/src/quoridor.py
quoridor/tests/__init__.py
quoridor/tests/test_quoridor.py
python_quoridor-0.1.2.dist-info/LICENSE.txt
python_quoridor-0.1.2.dist-info/METADATA
python_quoridor-0.1.2.dist-info/WHEEL
python_quoridor-0.1.2.dist-info/RECORD
