Metadata-Version: 2.1
Name: python-quoridor
Version: 0.1.2
Summary: python-quoridor is a a quoridor library for python, with move generation, move validation and support for common formats
License: MIT
Author: Tientjie
Author-email: tientjieit@gmail.com
Requires-Python: >=3.6,<4.0
Classifier: License :: OSI Approved :: MIT License
Classifier: Programming Language :: Python :: 3
Classifier: Programming Language :: Python :: 3.6
Classifier: Programming Language :: Python :: 3.7
Classifier: Programming Language :: Python :: 3.8
Classifier: Programming Language :: Python :: 3.9
Classifier: Programming Language :: Python :: 3.10
Classifier: Programming Language :: Python :: 3.11
